topsismy/myown.py
topsis_101703327-1.0.0.dist-info/LICENSE.py
topsis_101703327-1.0.0.dist-info/METADATA
topsis_101703327-1.0.0.dist-info/WHEEL
topsis_101703327-1.0.0.dist-info/entry_points.txt
topsis_101703327-1.0.0.dist-info/top_level.txt
topsis_101703327-1.0.0.dist-info/RECORD
