Metadata-Version: 2.1
Name: topsis-101703327
Version: 1.0.0
Summary: A Python package to implement topsis
Home-page: UNKNOWN
Author: Manjot Khaira
Author-email: khairamanjot2@gmail.com
License: MIT
Platform: UNKNOWN
Classifier: License :: OSI Approved :: MIT License
Classifier: Programming Language :: Python :: 3
Classifier: Programming Language :: Python :: 3.7
Requires-Dist: requests
